Metadata-Version: 2.1
Name: octofet
Version: 1.0.0
Summary: Raspberry Pi library for working with the Amperka Octofet – 8-channels switch board.
Home-page: https://github.com/amperka/OctofetPi/
Author: Amperka LLC
Author-email: dev@amperka.com
License: GPLv3
Platform: UNKNOWN
Classifier: Programming Language :: Python :: 3
Classifier: Programming Language :: Python :: 3.7
License-File: LICENSE
